quantumgrid/__init__.py
quantumgrid/cli.py
quantumgrid/femdvr.py
quantumgrid/potential.py
quantumgrid_examples/CO_vib_states_FEM_DVR.py
quantumgrid_examples/ECS_FEMDVR_diatomic_time_dep_vibration_H2.py
quantumgrid_examples/ECS_FEMDVR_diatomic_time_indep_vibration_H2.py
quantumgrid_examples/H2_vib_states_FEM_DVR.py
quantumgrid_examples/Time_dep_excitation_2_potential_curves.py
quantumgrid_examples/Two_electron_ECS.py
quantumgrid_examples/__init__.py
quantumgrid_examples/potcurve_CISDT_CO_ccpvDZ.dat
quantumgrid_examples/potcurve_CISD_H2_ccpvTZ.dat
quantumgrid-2.0.30.dist-info/AUTHORS.rst
quantumgrid-2.0.30.dist-info/LICENSE
quantumgrid-2.0.30.dist-info/METADATA
quantumgrid-2.0.30.dist-info/WHEEL
quantumgrid-2.0.30.dist-info/entry_points.txt
quantumgrid-2.0.30.dist-info/top_level.txt
quantumgrid-2.0.30.dist-info/RECORD
