Metadata-Version: 2.1
Name: quantumgrid
Version: 2.0.30
Summary: Exterior Complex Scaling Finite-Element Method Discrete Variable Representation grid for general physics problems.
Home-page: https://github.com/zstreeter/quantumgrid
Author: Zachary Streeter
Author-email: zlstreeter@lbl.gov
License: MIT license
Keywords: quantumgrid
Platform: UNKNOWN
Classifier: Development Status :: 2 - Pre-Alpha
Classifier: Intended Audience :: Developers
Classifier: License :: OSI Approved :: MIT License
Classifier: Natural Language :: English
Classifier: Programming Language :: Python :: 3
Classifier: Programming Language :: Python :: 3.7
Classifier: Programming Language :: Python :: 3.8
Requires-Python: >=3.7
Requires-Dist: Click (==7.1.2)
Requires-Dist: ffmpeg (==1.4)
Requires-Dist: cycler (==0.10.0)
Requires-Dist: fastcache (==1.1.0)
Requires-Dist: kiwisolver (==1.3.1)
Requires-Dist: matplotlib (==3.4.1)
Requires-Dist: mpmath (==1.1.0)
Requires-Dist: numpy (==1.20.2)
Requires-Dist: pyparsing (==2.4.7)
Requires-Dist: python-dateutil (==2.8.1)
Requires-Dist: scipy (==1.6.3)
Requires-Dist: six (==1.15.0)
Requires-Dist: sympy (==1.8)
Requires-Dist: tornado (==6.1)
Requires-Dist: sphinxcontrib-bibtex
